renardo_lib/Bang.py
renardo_lib/Chords.py
renardo_lib/Constants.py
renardo_lib/Key.py
renardo_lib/Logging.py
renardo_lib/Midi.py
renardo_lib/OSC3.py
renardo_lib/Players.py
renardo_lib/Repeat.py
renardo_lib/Root.py
renardo_lib/Scale.py
renardo_lib/TempoClock.py
renardo_lib/TimeVar.py
renardo_lib/__init__.py
renardo_lib/Code/__init__.py
renardo_lib/Code/foxdot_func_cmp.py
renardo_lib/Code/foxdot_live_function.py
renardo_lib/Code/foxdot_tokenize.py
renardo_lib/Code/foxdot_when_statement.py
renardo_lib/Code/main_lib.py
renardo_lib/Custom/__init__.py
renardo_lib/Custom/startup.py
renardo_lib/Extensions/PArp.py
renardo_lib/Extensions/__init__.py
renardo_lib/Extensions/SonicPiSynthDefImporter/__init__.py
renardo_lib/Extensions/SonicPiSynthDefImporter/generate_sonic_pi.py
renardo_lib/Extensions/VRender/Composer.py
renardo_lib/Extensions/VRender/MidiFactory.py
renardo_lib/Extensions/VRender/Sinsy.py
renardo_lib/Extensions/VRender/VRender.py
renardo_lib/Extensions/VRender/VoiceSpecificator.py
renardo_lib/Extensions/VRender/__init__.py
renardo_lib/Patterns/Generators.py
renardo_lib/Patterns/Main.py
renardo_lib/Patterns/Operations.py
renardo_lib/Patterns/PGroups.py
renardo_lib/Patterns/Parse.py
renardo_lib/Patterns/PlayString.py
renardo_lib/Patterns/Sequences.py
renardo_lib/Patterns/Utils.py
renardo_lib/Patterns/__init__.py
renardo_lib/ServerManager/__init__.py
renardo_lib/ServerManager/default_server.py
renardo_lib/Settings/__init__.py
renardo_lib/Settings/conf.py
renardo_lib/SynthDefManagement/BufferManagement.py
renardo_lib/SynthDefManagement/EffectManager.py
renardo_lib/SynthDefManagement/SimpleSynthDefs.py
renardo_lib/SynthDefManagement/SynthDefProxy.py
renardo_lib/SynthDefManagement/SynthDict.py
renardo_lib/SynthDefManagement/__init__.py
renardo_lib/SynthDefManagement/SCLangExperimentalPythonBindings/Env.py
renardo_lib/SynthDefManagement/SCLangExperimentalPythonBindings/NewPygenEffectClassUnused.py
renardo_lib-0.9.13.dist-info/LICENSE
renardo_lib-0.9.13.dist-info/METADATA
renardo_lib-0.9.13.dist-info/WHEEL
renardo_lib-0.9.13.dist-info/top_level.txt
renardo_lib-0.9.13.dist-info/RECORD
