Metadata-Version: 2.1
Name: renardo_lib
Version: 0.9.13
Summary: Python livecoding environment - New fork of FoxDot
Home-page: http://renardo.org/
Author: Elie Gavoty
Author-email: eliegavoty@free.fr
License: cc-by-sa-4.0
License-File: LICENSE
Requires-Dist: renardo-gatherer ==0.1.4.dev1
Requires-Dist: midiutil
